tulip/__init__.py
tulip_rdf-0.1.2.dist-info/LICENSE
tulip_rdf-0.1.2.dist-info/METADATA
tulip_rdf-0.1.2.dist-info/WHEEL
tulip_rdf-0.1.2.dist-info/top_level.txt
tulip_rdf-0.1.2.dist-info/RECORD
