Metadata-Version: 2.1
Name: tulip-rdf
Version: 0.1.2
Summary: TULIP RDF vocabulary
Home-page: https://github.com/julthep/tulip
Author: Julthep Nandakwang
Author-email: julthep@nandakwang.com
License: UNKNOWN
Platform: UNKNOWN
Classifier: Programming Language :: Python :: 3
Classifier: License :: OSI Approved :: GNU Lesser General Public License v3 or later (LGPLv3+)
Classifier: Operating System :: OS Independent
Requires-Python: >=3.6
